generated/__init__.py
generated/dbase/__init__.py
generated/dbase/enum_pre.py
moapy/ACI318-19_Beam.docx
moapy/EC2_wall.docx
moapy/__init__.py
moapy/alu_pre.py
moapy/api_url.py
moapy/auto_convert.py
moapy/calculator_asd.py
moapy/data_post.py
moapy/data_pre.py
moapy/dgncodeutil.py
moapy/engineers.py
moapy/enum_pre.py
moapy/geometry.py
moapy/hello.html
moapy/mdreporter.py
moapy/midasapi.py
moapy/midasapi.pyi
moapy/midasutil.py
moapy/midasutil_server.py
moapy/midasutil_web.py
moapy/rc_pre.py
moapy/ref_4.docx
moapy/reference.docx
moapy/reference_2.docx
moapy/reference_3.docx
moapy/steel_pre.py
moapy/symbol.py
moapy/test.py
moapy/test2.py
moapy/unit_converter.py
moapy/vector.py
moapy/version.py
moapy/designers_guide/__init__.py
moapy/designers_guide/design_editor_functions.py
moapy/designers_guide/func_execute.py
moapy/designers_guide/utils.py
moapy/designers_guide/core_engine/__init__.py
moapy/designers_guide/core_engine/content_calculator.py
moapy/designers_guide/core_engine/execute_calc_general.py
moapy/designers_guide/core_engine/schema_function_creator.py
moapy/designers_guide/resource/__init__.py
moapy/designers_guide/resource/component17.py
moapy/designers_guide/resource/component18.py
moapy/designers_guide/resource/component19.py
moapy/designers_guide/resource/component20.py
moapy/designers_guide/resource/component21.py
moapy/designers_guide/resource/component22.py
moapy/designers_guide/resource/component23.py
moapy/designers_guide/resource/component24.py
moapy/designers_guide/resource/component25.py
moapy/designers_guide/resource/component26.py
moapy/designers_guide/resource/component27.py
moapy/designers_guide/resource/component28.py
moapy/designers_guide/resource/component29.py
moapy/designers_guide/resource/component30.py
moapy/designers_guide/resource/component31.py
moapy/designers_guide/resource/component32.py
moapy/designers_guide/resource/component33.py
moapy/designers_guide/resource/component34.py
moapy/designers_guide/resource/component35.py
moapy-1.3.4.dist-info/METADATA
moapy-1.3.4.dist-info/WHEEL
moapy-1.3.4.dist-info/top_level.txt
moapy-1.3.4.dist-info/RECORD
