Metadata-Version: 2.1
Name: moapy
Version: 1.3.4
Summary: Midas Open API for Python
Home-page: https://github.com/MIDASIT-Co-Ltd/engineers-api-python
Author: bschoi
License: MIT
Requires-Dist: mdutils
Requires-Dist: numpy
Requires-Dist: matplotlib
Provides-Extra: full
Requires-Dist: toml ; extra == 'full'
Requires-Dist: openai-functions ; extra == 'full'
Requires-Dist: requests ; extra == 'full'
Requires-Dist: numpy ; extra == 'full'
Requires-Dist: json-strong-typing ; extra == 'full'
Requires-Dist: docstring-parser ; extra == 'full'
Requires-Dist: scipy ; extra == 'full'
Requires-Dist: pydantic (==2.10.4) ; extra == 'full'
Requires-Dist: mdutils ; extra == 'full'
Requires-Dist: mypy ; extra == 'full'
Requires-Dist: fastapi (==0.115.12) ; extra == 'full'
Requires-Dist: sectionproperties ; extra == 'full'
Requires-Dist: pandas ; extra == 'full'
Requires-Dist: jsonpointer ; extra == 'full'
Requires-Dist: concreteproperties ; extra == 'full'
Requires-Dist: openai ; extra == 'full'
Requires-Dist: matplotlib (==3.8.3) ; extra == 'full'
Requires-Dist: sympy ; extra == 'full'
Requires-Dist: antlr4-python3-runtime (==4.11) ; extra == 'full'
Requires-Dist: pytest ; extra == 'full'
Requires-Dist: jsonref ; extra == 'full'
Requires-Dist: diskcache ; extra == 'full'
Requires-Dist: trimesh ; extra == 'full'
Requires-Dist: embreex ; extra == 'full'
